bitcoin/__init__.py
bitcoin/bci.py
bitcoin/blocks.py
bitcoin/composite.py
bitcoin/deterministic.py
bitcoin/english.txt
bitcoin/main.py
bitcoin/mnemonic.py
bitcoin/py3specials.py
bitcoin/ripemd.py
bitcoin/stealth.py
bitcoin/transaction.py
pybtctools-0.2.0.dist-info/LICENSE
pybtctools-0.2.0.dist-info/WHEEL
pybtctools-0.2.0.dist-info/METADATA
pybtctools-0.2.0.dist-info/RECORD
