Metadata-Version: 2.1
Name: pybtctools
Version: 0.2.0
Summary: Python Bitcoin Tool
Home-page: http://github.com/danvergara/pybtctools
License: MIT
Author: Daniel Omar Vergara Pérez
Author-email: daniel.omar.vergara@gmail.com
Requires-Python: >=3.8,<4.0
Classifier: License :: OSI Approved :: MIT License
Classifier: Programming Language :: Python :: 3
Classifier: Programming Language :: Python :: 3.8
Classifier: Programming Language :: Python :: 3.9
Requires-Dist: importlib-metadata (>=4.8.1,<5.0.0); python_version < "3.8"
Project-URL: Documentation, https://pybtctools.readthedocs.io
Project-URL: Repository, http://github.com/danvergara/pybtctools
